setup.py
CFFIpp.egg-info/PKG-INFO
CFFIpp.egg-info/SOURCES.txt
CFFIpp.egg-info/dependency_links.txt
CFFIpp.egg-info/requires.txt
CFFIpp.egg-info/top_level.txt
cffipp/__init__.py
cffipp/cffipp.py
cffipp/cwrapper.py
cffipp/python_classer.py