Metadata-Version: 1.1
Name: CFFIpp
Version: 0.1.0.dev2
Summary: CFFI module for calling C++ code from within Python
Home-page: https://gitlab.com/rubdos/cffipp
Author: Ruben De Smet
Author-email: ruben.de.smet@rubdos.be
License: GPLv3
Platform: UNKNOWN
Classifier: Development Status :: 3 - Alpha
Classifier: Operating System :: OS Independent
Classifier: Programming Language :: Python
Classifier: Programming Language :: Python :: 2
Classifier: Programming Language :: Python :: 2.6
Classifier: Programming Language :: Python :: 2.7
Classifier: Programming Language :: Python :: 3
Classifier: Programming Language :: Python :: 3.2
Classifier: Programming Language :: Python :: 3.3
Classifier: Programming Language :: Python :: 3.4
Classifier: Programming Language :: Python :: 3.5
Classifier: Programming Language :: Python :: Implementation :: CPython
Classifier: Programming Language :: Python :: Implementation :: PyPy
Classifier: License :: OSI Approved :: GNU General Public License (GPL)
Classifier: Natural Language :: English
